sorno/__init__.py
sorno/debuggingutil.py
sorno/gitutil.py
sorno/loggingutil.py
sorno/pdfutil.py
sorno_py_scripts-0.48.8.data/scripts/sorno_alarm.py
sorno_py_scripts-0.48.8.data/scripts/sorno_amazon_reviews_scrape.py
sorno_py_scripts-0.48.8.data/scripts/sorno_amazon_wishlist_scrape.py
sorno_py_scripts-0.48.8.data/scripts/sorno_appcache_generator.py
sorno_py_scripts-0.48.8.data/scripts/sorno_attach_realdate.py
sorno_py_scripts-0.48.8.data/scripts/sorno_cloud_vision.py
sorno_py_scripts-0.48.8.data/scripts/sorno_compress_photos.py
sorno_py_scripts-0.48.8.data/scripts/sorno_download_all.py
sorno_py_scripts-0.48.8.data/scripts/sorno_dropbox.py
sorno_py_scripts-0.48.8.data/scripts/sorno_email.py
sorno_py_scripts-0.48.8.data/scripts/sorno_extract_spg_properties.py
sorno_py_scripts-0.48.8.data/scripts/sorno_facts.py
sorno_py_scripts-0.48.8.data/scripts/sorno_feedly.py
sorno_py_scripts-0.48.8.data/scripts/sorno_gcloud_bigquery.py
sorno_py_scripts-0.48.8.data/scripts/sorno_gcloud_pubsub_demo.py
sorno_py_scripts-0.48.8.data/scripts/sorno_gdoc.py
sorno_py_scripts-0.48.8.data/scripts/sorno_gdrive.py
sorno_py_scripts-0.48.8.data/scripts/sorno_grepchunks.py
sorno_py_scripts-0.48.8.data/scripts/sorno_gtasks.py
sorno_py_scripts-0.48.8.data/scripts/sorno_input_params_autovalue_converter.py
sorno_py_scripts-0.48.8.data/scripts/sorno_java_deps_graph.py
sorno_py_scripts-0.48.8.data/scripts/sorno_join_malls_info_in_csv.py
sorno_py_scripts-0.48.8.data/scripts/sorno_locate_git.py
sorno_py_scripts-0.48.8.data/scripts/sorno_ls.py
sorno_py_scripts-0.48.8.data/scripts/sorno_merge_pdfs.py
sorno_py_scripts-0.48.8.data/scripts/sorno_parse_test_logs.py
sorno_py_scripts-0.48.8.data/scripts/sorno_pdf_to_text.py
sorno_py_scripts-0.48.8.data/scripts/sorno_pick.py
sorno_py_scripts-0.48.8.data/scripts/sorno_podcast_downloader.py
sorno_py_scripts-0.48.8.data/scripts/sorno_protobuf_to_dict.py
sorno_py_scripts-0.48.8.data/scripts/sorno_realdate.py
sorno_py_scripts-0.48.8.dist-info/LICENSE
sorno_py_scripts-0.48.8.dist-info/METADATA
sorno_py_scripts-0.48.8.dist-info/WHEEL
sorno_py_scripts-0.48.8.dist-info/top_level.txt
sorno_py_scripts-0.48.8.dist-info/RECORD
