Metadata-Version: 2.1
Name: sorno-py-scripts
Version: 0.48.8
Summary: Herman Tai's python scripts all prefixed with "sorno_"
Home-page: https://github.com/hermantai/sorno-py-scripts
Download-URL: https://github.com/hermantai/sorno-py-scripts/archive/master.zip
Author: Herman Tai
Author-email: htaihm@gmail.com
License: APLv2
Classifier: Development Status :: 3 - Alpha
Classifier: Topic :: Utilities
Classifier: Topic :: Software Development :: Libraries
Classifier: License :: OSI Approved :: Apache Software License
Requires: beautifulsoup4
Requires: dropbox
Requires: feedparser
Requires: gitpython
Requires: oauth2client
Requires: google_api_python_client
Requires: humanfriendly
Requires: humanize
Requires: lxml
Requires: pillow
Requires: PyPDF2
Requires: python_dateutil
Requires: python_twitter
Requires: requests
Requires: six
Requires: tzlocal
Requires: sornobase
License-File: LICENSE
Requires-Dist: beautifulsoup4
Requires-Dist: dropbox
Requires-Dist: feedparser
Requires-Dist: gitpython
Requires-Dist: oauth2client
Requires-Dist: google-api-python-client
Requires-Dist: humanfriendly
Requires-Dist: humanize
Requires-Dist: lxml
Requires-Dist: pillow
Requires-Dist: PyPDF2
Requires-Dist: python-dateutil
Requires-Dist: python-twitter
Requires-Dist: requests
Requires-Dist: six
Requires-Dist: tzlocal
Requires-Dist: sornobase
